LICENSE
MANIFEST.in
README.rst
setup.py
btc_simple_wizard.egg-info/PKG-INFO
btc_simple_wizard.egg-info/SOURCES.txt
btc_simple_wizard.egg-info/dependency_links.txt
btc_simple_wizard.egg-info/requires.txt
btc_simple_wizard.egg-info/top_level.txt
simple_wizard/__init__.py
simple_wizard/apps.py
simple_wizard/components.py
simple_wizard/utils.py
simple_wizard/views.py
simple_wizard/static/simple_wizard/wizard.js
simple_wizard/templates/simple_wizard/crypto_pro_sign_modal.html
simple_wizard/templates/simple_wizard/wizard_base_modal.html
simple_wizard/templates/simple_wizard/wizard_modal.html
simple_wizard/templates/simple_wizard/wizard_modal_form.html
simple_wizard/templates/simple_wizard/wizard_modal_message.html