Metadata-Version: 1.1
Name: btc-simple-wizard
Version: 0.3
Summary: A simple application with some classes and scripts for wizard implementation.
Home-page: https://github.com/MEADez/btc-simple-manager
Author: MEADez
Author-email: m3adez@gmail.com
License: BSD License
Platform: UNKNOWN
Classifier: Environment :: Web Environment
Classifier: Framework :: Django
Classifier: Intended Audience :: Developers
Classifier: License :: OSI Approved :: BSD License
Classifier: Operating System :: OS Independent
Classifier: Programming Language :: Python :: 3.6
Classifier: Topic :: Internet :: WWW/HTTP
Classifier: Topic :: Internet :: WWW/HTTP :: Dynamic Content
